liteprofile.py
liteprofile-0.1.0.dist-info/licenses/LICENSE
liteprofile-0.1.0.dist-info/METADATA
liteprofile-0.1.0.dist-info/WHEEL
liteprofile-0.1.0.dist-info/entry_points.txt
liteprofile-0.1.0.dist-info/top_level.txt
liteprofile-0.1.0.dist-info/RECORD
