Metadata-Version: 2.4
Name: liteprofile
Version: 0.1.0
Summary: A lightweight, fast data profiling library built on Polars (with Pandas fallback).
Author: Inez Van Laer
License: MIT
Project-URL: Homepage, https://github.com/inezvl/liteprofile
Project-URL: Issues, https://github.com/inezvl/liteprofile/issues
Keywords: EDA,profiling,polars,pandas,duckdb,data
Classifier: Development Status :: 3 - Alpha
Classifier: Intended Audience :: Developers
Classifier: License :: OSI Approved :: MIT License
Classifier: Programming Language :: Python :: 3
Classifier: Topic :: Scientific/Engineering :: Information Analysis
Requires-Python: >=3.8
License-File: LICENSE
Requires-Dist: polars>=0.20.0
Requires-Dist: pandas>=2.0.0
Provides-Extra: duck
Requires-Dist: duckdb>=0.10.0; extra == "duck"
Provides-Extra: dev
Requires-Dist: ruff>=0.5.0; extra == "dev"
Requires-Dist: black>=24.0.0; extra == "dev"
Requires-Dist: mypy>=1.8.0; extra == "dev"
Requires-Dist: pytest>=8.0.0; extra == "dev"
Dynamic: license-file
